README.md
setup.cfg
setup.py
amzclients_sdk.egg-info/PKG-INFO
amzclients_sdk.egg-info/SOURCES.txt
amzclients_sdk.egg-info/dependency_links.txt
amzclients_sdk.egg-info/requires.txt
amzclients_sdk.egg-info/top_level.txt
aws_consoler/__init__.py
aws_consoler/cli.py
aws_consoler/logic.py
boto3/__init__.py
boto3/compat.py
boto3/crt.py
boto3/exceptions.py
boto3/session.py
boto3/utils.py
boto3/docs/__init__.py
boto3/docs/action.py
boto3/docs/attr.py
boto3/docs/base.py
boto3/docs/client.py
boto3/docs/collection.py
boto3/docs/docstring.py
boto3/docs/method.py
boto3/docs/resource.py
boto3/docs/service.py
boto3/docs/subresource.py
boto3/docs/utils.py
boto3/docs/waiter.py
boto3/dynamodb/__init__.py
boto3/dynamodb/conditions.py
boto3/dynamodb/table.py
boto3/dynamodb/transform.py
boto3/dynamodb/types.py
boto3/ec2/__init__.py
boto3/ec2/createtags.py
boto3/ec2/deletetags.py
boto3/resources/__init__.py
boto3/resources/action.py
boto3/resources/base.py
boto3/resources/collection.py
boto3/resources/factory.py
boto3/resources/model.py
boto3/resources/params.py
boto3/resources/response.py
boto3/s3/__init__.py
boto3/s3/constants.py
boto3/s3/inject.py
boto3/s3/transfer.py
botocore/__init__.py
botocore/args.py
botocore/auth.py
botocore/awsrequest.py
botocore/client.py
botocore/compat.py
botocore/compress.py
botocore/config.py
botocore/configloader.py
botocore/configprovider.py
botocore/credentials.py
botocore/discovery.py
botocore/endpoint.py
botocore/endpoint_provider.py
botocore/errorfactory.py
botocore/eventstream.py
botocore/exceptions.py
botocore/handlers.py
botocore/history.py
botocore/hooks.py
botocore/httpchecksum.py
botocore/httpsession.py
botocore/loaders.py
botocore/model.py
botocore/monitoring.py
botocore/paginate.py
botocore/parsers.py
botocore/regions.py
botocore/response.py
botocore/retryhandler.py
botocore/serialize.py
botocore/session.py
botocore/signers.py
botocore/stub.py
botocore/tokens.py
botocore/translate.py
botocore/useragent.py
botocore/utils.py
botocore/validate.py
botocore/waiter.py
botocore/crt/__init__.py
botocore/crt/auth.py
botocore/docs/__init__.py
botocore/docs/client.py
botocore/docs/docstring.py
botocore/docs/example.py
